jsonl2json/__init__.py
jsonl2json/jsonl_to_json.py
jsonl2json/utils.py
jsonl2json-1.0.0.dist-info/LICENSE.txt
jsonl2json-1.0.0.dist-info/METADATA
jsonl2json-1.0.0.dist-info/WHEEL
jsonl2json-1.0.0.dist-info/top_level.txt
jsonl2json-1.0.0.dist-info/RECORD
