Metadata-Version: 2.1
Name: jsonl2json
Version: 1.0.0
Summary: A Python library for converting data in the JSON Lines (.jsonl) format to the standard JSON (.json) format
Author-email: Ismail Ibrahim <ismailsoftdev@gmail.com>
Project-URL: Homepage, https://github.com/ismailsoftdev/jsonl2json
Project-URL: Bug Tracker, https://github.com/ismailsoftdev/jsonl2json/issues
Classifier: Programming Language :: Python :: 3
Classifier: License :: OSI Approved :: MIT License
Classifier: Operating System :: OS Independent
Requires-Python: >=3.7
License-File: LICENSE.txt
